maintenancemode/__init__.py
maintenancemode/admin.py
maintenancemode/http.py
maintenancemode/middleware.py
maintenancemode/models.py
maintenancemode/conf/__init__.py
maintenancemode/conf/urls/__init__.py
maintenancemode/conf/urls/defaults.py
maintenancemode/management/__init__.py
maintenancemode/management/commands/__init__.py
maintenancemode/management/commands/setmaintenance.py
maintenancemode/migrations/0001_initial.py
maintenancemode/migrations/0002_auto_20170920_1455.py
maintenancemode/migrations/0003_auto_20180227_0331.py
maintenancemode/migrations/__init__.py
maintenancemode/utils/__init__.py
maintenancemode/utils/settings.py
maintenancemode/utils/__pycache__/__init__.cpython-36.pyc
maintenancemode/utils/__pycache__/settings.cpython-36.pyc
maintenancemode/views/__init__.py
maintenancemode/views/defaults.py
maintenancemode/views/__pycache__/__init__.cpython-36.pyc
maintenancemode/views/__pycache__/defaults.cpython-36.pyc
django_maintenancemode_2-1.3.1.dist-info/AUTHORS
django_maintenancemode_2-1.3.1.dist-info/LICENSE
django_maintenancemode_2-1.3.1.dist-info/METADATA
django_maintenancemode_2-1.3.1.dist-info/WHEEL
django_maintenancemode_2-1.3.1.dist-info/top_level.txt
django_maintenancemode_2-1.3.1.dist-info/RECORD
