Metadata-Version: 2.1
Name: django-maintenancemode-2
Version: 1.3.1
Summary: Database-driven way to put your Django site into maintenance mode.
Home-page: https://github.com/alsoicode/django-maintenancemode-2
Author: Brandon Taylor
Author-email: alsoicode@gmail.com
License: APL
Platform: UNKNOWN
Classifier: Development Status :: 5 - Production/Stable
Classifier: Environment :: Web Environment
Classifier: Framework :: Django
Classifier: Intended Audience :: Developers
Classifier: License :: OSI Approved :: Apache Software License
Classifier: Operating System :: OS Independent
Classifier: Programming Language :: Python
Classifier: Topic :: Utilities
Requires-Dist: django
